{
  "clinicalCases": [
    {
      "id": 1,
      "name": "Caso clínico 1",
      "specialty": "Cirugía General",
      "question": [
        {
          "id": 1,
          "text": "¿Cuál es el tratamiento más adecuado para una fractura de hueso?",
          "correctAnswer": 3,
          "answers": [
            {
              "id": 1,
              "option": "A",
              "text": "Antibióticos",
              "feedback": "Respuesta incorrecta. Los antibióticos no son el tratamiento principal para una fractura de hueso."
            },
            {
              "id": 2,
              "option": "B",
              "text": "Fisioterapia",
              "feedback": "Respuesta incorrecta. La fisioterapia puede ser útil durante la rehabilitación después de una fractura, pero no es el tratamiento inicial."
            },
            {
              "id": 3,
              "option": "C",
              "text": "Inmovilización",
              "feedback": "Respuesta correcta. La inmovilización es un tratamiento común para las fracturas óseas, ya que ayuda a estabilizar y permitir la recuperación adecuada del hueso fracturado."
            },
            {
              "id": 4,
              "option": "D",
              "text": "Receta casera",
              "feedback": "Respuesta incorrecta. Son mitos."
            }
          ]
        }
      ],
      "feedback": "En este caso clínico, la respuesta correcta es la opción C: Inmovilización. La inmovilización es un tratamiento común y efectivo para las fracturas de hueso, ya que ayuda a estabilizar la lesión y promover la correcta recuperación del hueso fracturado."
    },
    {
      "id": 2,
      "name": "Caso clínico 2",
      "specialty": "Cardiología",
      "question": [
        {
          "id": 1,
          "text": "¿Cuál es el diagnóstico más probable para un paciente con dolor en el pecho, opresión y dificultad para respirar?",
          "correctAnswer": 1,
          "answers": [
            {
              "id": 1,
              "option": "A",
              "text": "Infarto de miocardio",
              "feedback": "Respuesta correcta. Los síntomas descritos son comunes en un infarto de miocardio, una condición grave que requiere atención médica urgente."
            },
            {
              "id": 2,
              "option": "B",
              "text": "Neumonía",
              "feedback": "Respuesta incorrecta. Aunque la neumonía puede causar dolor en el pecho y dificultad para respirar, no suele presentarse como opresión."
            },
            {
              "id": 3,
              "option": "C",
              "text": "Ataque de ansiedad",
              "feedback": "Respuesta incorrecta. Si bien la ansiedad puede provocar síntomas similares, el dolor en el pecho y la opresión deben ser evaluados adecuadamente para descartar otras causas más graves."
            },
            {
              "id": 4,
              "option": "D",
              "text": "Receta casera",
              "feedback": "Respuesta incorrecta. Son mitos."
            }
          ]
        }
      ],
      "feedback": "En este caso clínico, la respuesta correcta es la opción A: Infarto de miocardio. Los síntomas de dolor en el pecho, opresión y dificultad para respirar son indicativos de un posible infarto de miocardio, una emergencia médica que requiere atención inmediata."
    },
    {
      "id": 3,
      "name": "Caso clínico 3",
      "specialty": "Oncología",
      "question": [
        {
          "id": 1,
          "text": "¿Cuál es el tratamiento más apropiado?",
          "correctAnswer": 3,
          "answers": [
            {
              "id": 1,
              "option": "A",
              "text": "Radioterapia",
              "feedback": "Respuesta incorrecta. La radioterapia no es el tratamiento principal para esta afección."
            },
            {
              "id": 2,
              "option": "B",
              "text": "Cirugía",
              "feedback": "Respuesta incorrecta. La cirugía puede no ser necesaria o apropiada en este caso."
            },
            {
              "id": 3,
              "option": "C",
              "text": "Quimioterapia",
              "feedback": "Respuesta correcta. La quimioterapia es el tratamiento principal para el cáncer en etapas avanzadas."
            },
            {
              "id": 4,
              "option": "D",
              "text": "Receta casera",
              "feedback": "Respuesta incorrecta. Son mitos."
            }
          ]
        }
      ],
      "feedback": "En este caso clínico, la respuesta correcta es la opción C: Quimioterapia. La quimioterapia es el tratamiento principal para el cáncer en etapas avanzadas, ayudando a combatir las células cancerosas y controlar la progresión de la enfermedad."
    },
    {
      "id": 4,
      "name": "Caso clínico 4",
      "specialty": "Endocrinología",
      "question": [
        {
          "id": 1,
          "text": "¿Cuál es el diagnóstico más probable?",
          "correctAnswer": 2,
          "answers": [
            {
              "id": 1,
              "option": "A",
              "text": "Hipotiroidismo",
              "feedback": "Respuesta incorrecta. El hipotiroidismo se caracteriza por síntomas como fatiga, aumento de peso y sensibilidad al frío."
            },
            {
              "id": 2,
              "option": "B",
              "text": "Diabetes tipo 2",
              "feedback": "Respuesta correcta. La diabetes tipo 2 se caracteriza por resistencia a la insulina y niveles elevados de glucosa en sangre."
            },
            {
              "id": 3,
              "option": "C",
              "text": "Hipertiroidismo",
              "feedback": "Respuesta incorrecta. El hipertiroidismo se caracteriza por síntomas como pérdida de peso, nerviosismo e intolerancia al calor."
            },
            {
              "id": 4,
              "option": "D",
              "text": "Receta casera",
              "feedback": "Respuesta incorrecta. Son mitos."
            }
          ]
        }
      ],
      "feedback": "En este caso clínico, la respuesta correcta es la opción B: Diabetes tipo 2. Los síntomas descritos son más consistentes con la diabetes tipo 2, una condición crónica que se caracteriza por resistencia a la insulina y niveles elevados de glucosa en sangre."
    },
    {
      "id": 5,
      "name": "Caso clínico 5",
      "specialty": "Psiquiatría",
      "question": [
        {
          "id": 1,
          "text": "¿Cuál es el tratamiento más adecuado para un paciente con depresión mayor?",
          "correctAnswer": 4,
          "answers": [
            {
              "id": 1,
              "option": "A",
              "text": "Ansiolíticos",
              "feedback": "Respuesta incorrecta. Los ansiolíticos no son el tratamiento principal para la depresión mayor."
            },
            {
              "id": 2,
              "option": "B",
              "text": "Antidepresivos tricíclicos",
              "feedback": "Respuesta incorrecta. Los antidepresivos tricíclicos pueden ser una opción de tratamiento, pero no son de primera elección debido a sus efectos secundarios."
            },
            {
              "id": 3,
              "option": "C",
              "text": "Terapia de electroconvulsiva (TEC)",
              "feedback": "Respuesta incorrecta. La terapia de electroconvulsiva puede ser utilizada en casos graves y resistentes de depresión, pero no es el tratamiento inicial."
            },
            {
              "id": 4,
              "option": "D",
              "text": "Antidepresivos inhibidores selectivos de la recaptación de serotonina (ISRS)",
              "feedback": "Respuesta correcta. Los antidepresivos ISRS son la primera línea de tratamiento para la depresión mayor debido a su eficacia y menor riesgo de efectos secundarios graves."
            }
          ]
        }
      ],
      "feedback": "En este caso clínico, la respuesta correcta es la opción D: Antidepresivos inhibidores selectivos de la recaptación de serotonina (ISRS). Estos fármacos son considerados como el tratamiento de elección para la depresión mayor debido a su efectividad y perfil de efectos secundarios más favorable."
    }
  ]
}
